schematic/__init__.py
schematic/accesstokens/__init__.py
schematic/accesstokens/client.py
schematic/accesstokens/raw_client.py
schematic/accesstokens/types/__init__.py
schematic/accesstokens/types/issue_temporary_access_token_response.py
schematic/accounts/__init__.py
schematic/accounts/client.py
schematic/accounts/raw_client.py
schematic/accounts/types/__init__.py
schematic/accounts/types/count_api_keys_params.py
schematic/accounts/types/count_api_keys_response.py
schematic/accounts/types/count_api_requests_params.py
schematic/accounts/types/count_api_requests_response.py
schematic/accounts/types/create_api_key_response.py
schematic/accounts/types/create_environment_response.py
schematic/accounts/types/delete_api_key_response.py
schematic/accounts/types/delete_environment_response.py
schematic/accounts/types/get_api_key_response.py
schematic/accounts/types/get_api_request_response.py
schematic/accounts/types/get_environment_response.py
schematic/accounts/types/list_api_keys_params.py
schematic/accounts/types/list_api_keys_response.py
schematic/accounts/types/list_api_requests_params.py
schematic/accounts/types/list_api_requests_response.py
schematic/accounts/types/list_environments_params.py
schematic/accounts/types/list_environments_response.py
schematic/accounts/types/quickstart_response.py
schematic/accounts/types/update_api_key_response.py
schematic/accounts/types/update_environment_response.py
schematic/base_client.py
schematic/billing/__init__.py
schematic/billing/client.py
schematic/billing/raw_client.py
schematic/billing/types/__init__.py
schematic/billing/types/count_billing_products_params.py
schematic/billing/types/count_billing_products_response.py
schematic/billing/types/count_customers_params.py
schematic/billing/types/count_customers_response.py
schematic/billing/types/delete_billing_product_response.py
schematic/billing/types/delete_product_price_response.py
schematic/billing/types/list_billing_prices_params.py
schematichq-1.1.5.dist-info/LICENSE
schematichq-1.1.5.dist-info/METADATA
schematichq-1.1.5.dist-info/WHEEL
schematichq-1.1.5.dist-info/RECORD
